arffToDataFrame/__init__.py
arffToDataFrame/main.py
arffToDataFrame-1.2.dist-info/METADATA
arffToDataFrame-1.2.dist-info/WHEEL
arffToDataFrame-1.2.dist-info/entry_points.txt
arffToDataFrame-1.2.dist-info/top_level.txt
arffToDataFrame-1.2.dist-info/RECORD
