Metadata-Version: 2.1
Name: arffToDataFrame
Version: 1.2
Summary: A package to convert ARFF files to pandas DataFrames.
Home-page: https://github.com/ammarhaider16/arff-to-dataframe
Author: Ammar Haider
Author-email: ammarhaider1629@gmail.com
Requires-Dist: liac-arff >=2.5.0
Requires-Dist: pandas >=2.2.1
